TDS/__init__.py
osve_wrapper/__init__.py
osve_wrapper/osve_advanced_wrapper.py
osve_wrapper/commons/__init__.py
osve_wrapper/commons/eps_cfg_handler.py
osve_wrapper/commons/os_utils.py
osve_wrapper/commons/spice_kernels_utils.py
osve_wrapper/commons/timeline_handling.py
osve_wrapper/templates/config_osve_template.json
osve_wrapper/templates/osve_wrapper_default_values.json
osve_wrapper/templates/session_file.json
osve_wrapper/templates/CONFIG/top_obs_dummy.def
osve_wrapper/templates/CONFIG/AGE/aareadme.txt
osve_wrapper/templates/CONFIG/ISE/aareadme.txt
osve_wrapper/templates/old/config_osve_template_202202.json
osve_wrapper/templates/old/config_osve_template_save.json
osve_wrapper/templates/old/convert_brf.py
osve_wrapper/templates/old/eps.cfg
osve_wrapper/templates/old/events.juice.def
osve_wrapper/templates/old/response_nadir.json
osve_wrapper/templates/old/units.def
test/__init__.py
test/osve_test.py
test/test_eps_cfg_handler.py
test/test_osve_advanced_wrapper.py
test/test_osve_wrapper.py
test/test_osve_wrapper_simple_script.py
osve_wrapper-0.2.5.dist-info/METADATA
osve_wrapper-0.2.5.dist-info/WHEEL
osve_wrapper-0.2.5.dist-info/entry_points.txt
osve_wrapper-0.2.5.dist-info/top_level.txt
osve_wrapper-0.2.5.dist-info/RECORD
