Metadata-Version: 2.1
Name: osve-wrapper
Version: 0.2.5
Summary: Python package for OSVE wrapping
Home-page: https://juigitlab.esac.esa.int/core-system/uplink/osve_wrapper
Author: JUICE SOC team
Author-email: juice_soc@cosmos.esa.int
Keywords: esa,JUICE,EPS,planetary,space,metrics,trajectory,assessment,crema
Requires-Dist: esac-juice-pyutils>=0.3.2
Requires-Dist: osve>=2.0.0
Requires-Dist: rst2html5>=2.0
